pg_metadata/Cast.py
pg_metadata/Comment.py
pg_metadata/DDL.py
pg_metadata/Database.py
pg_metadata/Diff.py
pg_metadata/EventTrigger.py
pg_metadata/Extension.py
pg_metadata/ForeignServer.py
pg_metadata/ForeignTable.py
pg_metadata/Function.py
pg_metadata/Grabber.py
pg_metadata/Grant.py
pg_metadata/Namespace.py
pg_metadata/Owner.py
pg_metadata/Procedure.py
pg_metadata/Publication.py
pg_metadata/Sequence.py
pg_metadata/Subscription.py
pg_metadata/System.py
pg_metadata/Table.py
pg_metadata/TableColumn.py
pg_metadata/TableConstraint.py
pg_metadata/TableIndex.py
pg_metadata/TableSettings.py
pg_metadata/TableTrigger.py
pg_metadata/View.py
pg_metadata/__init__.py
pg_metadata-1.1.13.dist-info/LICENSE
pg_metadata-1.1.13.dist-info/METADATA
pg_metadata-1.1.13.dist-info/WHEEL
pg_metadata-1.1.13.dist-info/top_level.txt
pg_metadata-1.1.13.dist-info/RECORD
