Metadata-Version: 2.1
Name: pg-metadata
Version: 1.1.13
Summary: PostgreSQL metadata grabber and comparer
Home-page: https://github.com/ish1mura/pg_metadata
Author: ish1mura
Author-email: ek.dummy@gmail.com
License: UNKNOWN
Platform: UNKNOWN
Classifier: Programming Language :: Python :: 3
Classifier: License :: OSI Approved :: MIT License
Classifier: Operating System :: OS Independent
License-File: LICENSE
Requires-Dist: psycopg2-binary
